{
	"plants": [
		{
			"name": "Sweet Corn",
			"method": [
				{
					"type": "seed",
					"durationMin": 70,
					"durationMax": 90,
					"cycles": [
						{
							"start": 0215,
							"end": 0415
						},
						{
							"start": 0715,
							"end": 0831
						}
					]
				}
			]
		},
		{
			"name": "Sweet Corn 2",
			"method": [
				{
					"type": "seed",
					"durationMin": 70,
					"durationMax": 90,
					"cycles": [
						{
							"start": 0215,
							"end": 0415
						},
						{
							"start": 0715,
							"end": 0831
						}
					]
				}
			]
		}
	]
}